eos_midi/__init__.py
eos_midi/__main__.py
eos_midi/eos.py
eos_midi/eos_object/__init__.py
eos_midi/eos_object/channel.py
eos_midi/eos_object/fader.py
eos_midi/eos_object/macro.py
eos_midi/midi_controller.py
eos_midi/pad.py
eos_midi-0.1.1.dist-info/LICENSE
eos_midi-0.1.1.dist-info/METADATA
eos_midi-0.1.1.dist-info/WHEEL
eos_midi-0.1.1.dist-info/RECORD
