Metadata-Version: 2.1
Name: eos_midi
Version: 0.1.1
Summary: Controller to control EOS with Launchpad Mini Mk3 for ENS
Home-page: https://git.soyouzpanda.com/soyouzpanda/kfet_launchpad_controller
License: MIT
Author: soyouzpanda
Author-email: soyouzpanda@soyouzpanda.fr
Requires-Python: >=3.7,<4
Classifier: Development Status :: 2 - Pre-Alpha
Classifier: Intended Audience :: Developers
Classifier: License :: OSI Approved :: MIT License
Classifier: Natural Language :: English
Classifier: Programming Language :: Python :: 3
Classifier: Programming Language :: Python :: 3.7
Classifier: Programming Language :: Python :: 3.8
Classifier: Programming Language :: Python :: 3.9
Classifier: Programming Language :: Python :: 3.10
Classifier: Programming Language :: Python :: 3.11
Classifier: Programming Language :: Python :: 3.12
Classifier: Programming Language :: Python :: 3.5
Classifier: Programming Language :: Python :: 3.6
Requires-Dist: lpminimk3
Requires-Dist: python-osc
